{
  "question_filename": "P3_2_03_00043_53504.png",
  "id": "00043_53504",
  "question_info": [
    {
      "question_grade": "P3",
      "question_term": 2,
      "question_unit": "03",
      "question_topic": "3203004",
      "question_topic_name": "지름의 성질 알아보기",
      "question_type1": "단답형",
      "question_type2": 2,
      "question_condition": 0,
      "question_sector1": "이해",
      "question_sector2": "도형과 측정",
      "question_step": "기본",
      "question_difficulty": 3,
      "question_contents": 0
    }
  ],
  "OCR_info": [
    {
      "figure_text": null,
      "question_text": "원의 지름에 대한 설명으로 옳은 것을 찾아 기호를 쓰시오. ㉠ 한 원에서 가장 짧은 선분입니다.㉡ 원 위의 두 점을 이은 선분 중에서 원의 중심을 지나는 선분입니다.",
      "question_bbox": [
        {
          "type": "line",
          "bbox": [
            18,
            1,
            346,
            17
          ],
          "text": null
        },
        {
          "type": "line",
          "bbox": [
            19,
            21,
            229,
            58
          ],
          "text": null
        },
        {
          "type": "line",
          "bbox": [
            19,
            58,
            419,
            79
          ],
          "text": null
        },
        {
          "type": "paragraph",
          "bbox": [
            16,
            1,
            423,
            79
          ],
          "text": "원의 지름에 대한 설명으로 옳은 것을 찾아 기호를 쓰시오. ㉠ 한 원에서 가장 짧은 선분입니다.㉡ 원 위의 두 점을 이은 선분 중에서 원의 중심을 지나는 선분입니다."
        }
      ]
    }
  ]
}