{
  "question_filename": "P5_1_01_00042_30453.png",
  "id": "00042_30453",
  "question_info": [
    {
      "question_grade": "P5",
      "question_term": 1,
      "question_unit": "01",
      "question_topic": "5101002",
      "question_topic_name": "곱셈과 나눗셈이 섞여 있는 식의 계산",
      "question_type1": "단답형",
      "question_type2": 2,
      "question_condition": 0,
      "question_sector1": "문제해결",
      "question_sector2": "수와 연산",
      "question_step": "실생활응용",
      "question_difficulty": 2,
      "question_contents": 0
    }
  ],
  "OCR_info": [
    {
      "figure_text": null,
      "question_text": "연필 $15$타를 $6$사람에게 똑같이 나누어 주려고 합니다. 한 사람에게 몇 자루씩 나누어주면 되는지 하나의 식으로 만들어 구하시오.",
      "question_bbox": [
        {
          "type": "line",
          "bbox": [
            18,
            1,
            743,
            17
          ],
          "text": null
        },
        {
          "type": "paragraph",
          "bbox": [
            16,
            1,
            745,
            22
          ],
          "text": "연필 $15$타를 $6$사람에게 똑같이 나누어 주려고 합니다. 한 사람에게 몇 자루씩 나누어주면 되는지 하나의 식으로 만들어 구하시오."
        }
      ]
    }
  ]
}