{
  "question_filename": "P5_1_06_00044_39701.png",
  "id": "00044_39701",
  "question_info": [
    {
      "question_grade": "P5",
      "question_term": 1,
      "question_unit": "06",
      "question_topic": "5106025",
      "question_topic_name": "사다리꼴의 넓이 구하기",
      "question_type1": "단답형",
      "question_type2": 1,
      "question_condition": 0,
      "question_sector1": "이해",
      "question_sector2": "도형과 측정",
      "question_step": "기본",
      "question_difficulty": 3,
      "question_contents": 0
    }
  ],
  "OCR_info": [
    {
      "figure_text": null,
      "question_text": "오른쪽 평행사변형의 넓이가 $96cm²$일 때 왼쪽 사다리꼴의 넓이는 몇 $cm²$입니까?",
      "question_bbox": [
        {
          "type": "line",
          "bbox": [
            18,
            1,
            480,
            17
          ],
          "text": null
        },
        {
          "type": "image",
          "bbox": [
            22,
            24,
            319,
            82
          ],
          "text": null
        },
        {
          "type": "paragraph",
          "bbox": [
            16,
            1,
            482,
            21
          ],
          "text": "오른쪽 평행사변형의 넓이가 $96cm²$일 때 왼쪽 사다리꼴의 넓이는 몇 $cm²$입니까?"
        }
      ]
    }
  ]
}