{
  "question_filename": "P6_2_06_00043_97263.png",
  "id": "00043_97263",
  "question_info": [
    {
      "question_grade": "P6",
      "question_term": 2,
      "question_unit": "06",
      "question_topic": "6206002",
      "question_topic_name": "원기둥의 구성 요소",
      "question_type1": "선택형",
      "question_type2": 1,
      "question_condition": 0,
      "question_sector1": "이해",
      "question_sector2": "도형과 측정",
      "question_step": "기본",
      "question_difficulty": 2,
      "question_contents": 0
    }
  ],
  "OCR_info": [
    {
      "figure_text": null,
      "question_text": "다음과 같은 원기둥의 높이만$ 2$배로 늘리면 어떤 모양의 원기둥이 됩니까? ① ② ③ ④ ⑤",
      "question_bbox": [
        {
          "type": "line",
          "bbox": [
            18,
            1,
            438,
            16
          ],
          "text": null
        },
        {
          "type": "image",
          "bbox": [
            20,
            21,
            130,
            517
          ],
          "text": null
        },
        {
          "type": "paragraph",
          "bbox": [
            16,
            1,
            440,
            21
          ],
          "text": "다음과 같은 원기둥의 높이만$ 2$배로 늘리면 어떤 모양의 원기둥이 됩니까? ① ② ③ ④ ⑤"
        }
      ]
    }
  ]
}